pinax/__init__.py
pinax/eventlog/__init__.py
pinax/eventlog/admin.py
pinax/eventlog/mixins.py
pinax/eventlog/models.py
pinax/eventlog/signals.py
pinax/eventlog/stats.py
pinax/eventlog/migrations/0001_initial.py
pinax/eventlog/migrations/0002_alter_log_id.py
pinax/eventlog/migrations/__init__.py
pinax/eventlog/tests/__init__.py
pinax/eventlog/tests/tests.py
pinax_eventlog-6.0.0.dist-info/licenses/AUTHORS
pinax_eventlog-6.0.0.dist-info/licenses/LICENSE
pinax_eventlog-6.0.0.dist-info/METADATA
pinax_eventlog-6.0.0.dist-info/WHEEL
pinax_eventlog-6.0.0.dist-info/top_level.txt
pinax_eventlog-6.0.0.dist-info/RECORD
